serenade_flow/__init__.py
serenade_flow/pipeline.py
andy_serenade_flow-1.2.6.dist-info/METADATA
andy_serenade_flow-1.2.6.dist-info/WHEEL
andy_serenade_flow-1.2.6.dist-info/licenses/LICENSE
andy_serenade_flow-1.2.6.dist-info/RECORD
